aeat/__about__.py
aeat/__init__.py
aeat/utils.py
aeat/wsdl.py
aeat/xml_signing.py
aeat/zeep_plugins.py
aeat/rest_framework/__init__.py
aeat/rest_framework/complex_types_v2.py
aeat/rest_framework/complex_types_v5.py
aeat/rest_framework/fields.py
aeat/rest_framework/serializers.py
aeat/rest_framework/validators.py
aeat_web_services-2.0.2.dist-info/DESCRIPTION.rst
aeat_web_services-2.0.2.dist-info/METADATA
aeat_web_services-2.0.2.dist-info/RECORD
aeat_web_services-2.0.2.dist-info/WHEEL
aeat_web_services-2.0.2.dist-info/metadata.json
aeat_web_services-2.0.2.dist-info/top_level.txt
