Metadata-Version: 2.0
Name: aeat-web-services
Version: 2.0.2
Summary: Spanish Tax Agency Electronic Office (AEAT) Integration
Home-page: https://github.com/initios/aeat-web-services
Author: Initios Desarrollos
Author-email: dev@initios.com
License: MIT
Platform: UNKNOWN
Classifier: Programming Language :: Python
Classifier: Programming Language :: Python :: 3.6
Classifier: Development Status :: 5 - Production/Stable
Classifier: License :: OSI Approved :: MIT License
Requires-Python: >=3.4,<3.7
Requires-Dist: lxml (<4.2.0,>=4.1.1)
Requires-Dist: xmlsec (<1.4.0,>=1.3.3)
Requires-Dist: zeep (<2.5.0,>=2.4.0)
